nulldrop/__init__.py
nulldrop/client.py
nulldrop/exceptions.py
nulldrop-1.0.3.dist-info/METADATA
nulldrop-1.0.3.dist-info/WHEEL
nulldrop-1.0.3.dist-info/licenses/LICENSE
nulldrop-1.0.3.dist-info/RECORD
