Metadata-Version: 2.4
Name: nulldrop
Version: 1.0.3
Summary: Python SDK for the NullDrop File Hosting API
Project-URL: Homepage, https://github.com/Null-Tools-Open/nulldrop-pysdk
Author-email: Ais <haxmc@proton.me>
License: MIT
License-File: LICENSE
Requires-Python: >=3.8
Requires-Dist: requests>=2.28
